AUTHORS
LICENSE
MANIFEST.in
README.rst
setup.py
netengine/__init__.py
netengine/exceptions.py
netengine/utils.py
netengine.egg-info/PKG-INFO
netengine.egg-info/SOURCES.txt
netengine.egg-info/dependency_links.txt
netengine.egg-info/not-zip-safe
netengine.egg-info/requires.txt
netengine.egg-info/top_level.txt
netengine/backends/__init__.py
netengine/backends/base.py
netengine/backends/dummy.py
netengine/backends/http/__init__.py
netengine/backends/http/airos.py
netengine/backends/http/base.py
netengine/backends/snmp/__init__.py
netengine/backends/snmp/airos.py
netengine/backends/snmp/base.py
netengine/backends/snmp/openwrt.py
netengine/backends/ssh/__init__.py
netengine/backends/ssh/airos.py
netengine/backends/ssh/base.py
netengine/backends/ssh/openwrt.py
tests/__init__.py
tests/base.py
tests/dummy.py
tests/settings.py
tests/http/__init__.py
tests/http/airos.py
tests/http/base.py
tests/snmp/__init__.py
tests/snmp/airos.py
tests/snmp/base.py
tests/snmp/openwrt.py
tests/ssh/__init__.py
tests/ssh/airos.py
tests/ssh/base.py
tests/ssh/openwrt.py