Metadata-Version: 1.1
Name: netengine
Version: 0.1.alpha
Summary: Abstraction layer for extracting information from network devices.
Home-page: https://github.com/nemesisdesign/netengine
Author: Federico Capoano (nemesisdesign)
Author-email: ninux-dev@ml.ninux.org
License: MIT
Platform: UNKNOWN
Classifier: Development Status :: 1 - Planning
Classifier: Environment :: Console
Classifier: Intended Audience :: Developers
Classifier: License :: OSI Approved :: MIT License
Classifier: Operating System :: OS Independent
Classifier: Programming Language :: Python
Classifier: Topic :: System :: Networking
